MANIFEST.in
README.rst
setup.cfg
setup.py
pyconfy/__init__.py
pyconfy/actions.py
pyconfy/api.py
pyconfy.egg-info/PKG-INFO
pyconfy.egg-info/SOURCES.txt
pyconfy.egg-info/dependency_links.txt
pyconfy.egg-info/top_level.txt