Metadata-Version: 1.1
Name: pyconfy
Version: 0.3
Summary: An API wrapper for Atlassian Confluence
Home-page: https://github.com/muddytm/confy
Author: Caleb Hawkins
Author-email: hawkins.caleb93@gmail.com
License: UNKNOWN
Download-URL: https://github.com/muddytm/confy/tarball/0.2
Keywords: confluence
Platform: UNKNOWN
